observatory/__init__.py
observatory/data_types.py
observatory/events.py
observatory/publish_subscribe.py
observatory/thread_safe.py
observatory-2.0.0.dist-info/WHEEL
observatory-2.0.0.dist-info/METADATA
observatory-2.0.0.dist-info/licenses/LICENSE
observatory-2.0.0.dist-info/RECORD
