Metadata-Version: 2.1
Name: observatory
Version: 2.0.0
Summary: Observable, event-driven python!
Keywords: event,observer,observability,observables,pubsub,pub-sub,publish,subscribe
Author: Ed Whetstone
Requires-Python: >=3.11
Classifier: Intended Audience :: Developers
Classifier: License :: OSI Approved :: MIT License
Classifier: Operating System :: OS Independent
Classifier: Programming Language :: Python :: 3
Classifier: Programming Language :: Python :: 3.11
Classifier: Topic :: Software Development :: Libraries :: Python Modules
Provides-Extra: dev
Requires-Dist: pre-commit>=3.2.0; extra == "dev"
Project-URL: documentation, https://github.com/sharpencrag/observatory#readme
Project-URL: homepage, https://github.com/sharpencrag/observatory
Project-URL: repository, https://github.com/sharpencrag/observatory
